consulta_investimentos/__init__.py
consulta_investimentos/ativos_cotacoes/__init__.py
consulta_investimentos/ativos_cotacoes/cotacoes.py
consulta_investimentos/ativos_posicao/__init__.py
consulta_investimentos/ativos_posicao/posicao.py
consulta_investimentos/cli.py
consulta_investimentos/moeda_cotacao/__init__.py
consulta_investimentos/moeda_cotacao/moedas.py
consulta_investimentos/moeda_cotacao/valida_moeda.py
consulta_investimentos/utils/__init__.py
consulta_investimentos/utils/append.py
consulta_investimentos/utils/arquivo.py
consulta_investimentos/utils/data_functions.py
consulta_investimentos/yfinance_exemple.py
consulta_investimentos-5.0.1.dist-info/entry_points.txt
consulta_investimentos-5.0.1.dist-info/LICENSE
consulta_investimentos-5.0.1.dist-info/WHEEL
consulta_investimentos-5.0.1.dist-info/METADATA
consulta_investimentos-5.0.1.dist-info/RECORD
