Metadata-Version: 2.1
Name: consulta-investimentos
Version: 5.0.1
Summary: Baixa infos diversas de ativos financeiros.
Author: Vinicius Maciel
Author-email: vinimaciel01@gmail.com
Requires-Python: >=3.9,<4.0
Classifier: Programming Language :: Python :: 3
Classifier: Programming Language :: Python :: 3.10
Classifier: Programming Language :: Python :: 3.9
Requires-Dist: bs4 (>=0.0.1,<0.0.2)
Requires-Dist: click (>=8.1.2,<9.0.0)
Requires-Dist: openpyxl (>=3.0.9,<4.0.0)
Requires-Dist: pandas (>=1.4.1,<2.0.0)
Requires-Dist: pandas-datareader (>=0.10.0,<0.11.0)
Requires-Dist: pycryptodome (>=3.16.0,<4.0.0)
Requires-Dist: pycryptodomex (>=3.16.0,<4.0.0)
Requires-Dist: requests (>=2.27.1,<3.0.0)
Requires-Dist: selenium (>=4.1.2,<5.0.0)
Requires-Dist: yfinance (>=0.2.3,<0.3.0)
